{
  "entries": [
    {
      "date": "",
      "concept": "test",
      "entry": "test",
      "moodId": "1",
      "id": 10
    },
    {
      "date": "",
      "concept": "test",
      "entry": "test",
      "moodId": "3",
      "id": 11
    },
    {
      "date": "",
      "concept": "test",
      "entry": "test",
      "moodId": "2",
      "id": 14
    },
    {
      "date": "",
      "concept": "test",
      "entry": "test",
      "moodId": "4",
      "id": 15
    },
    {
      "date": "2021-02-15",
      "concept": "test",
      "entry": "Let's try again and see what happens",
      "moodId": "2",
      "id": 16
    }
  ],
  "moods": [
    {
      "label": "Fine",
      "id": 1
    },
    {
      "label": "Proud",
      "id": 2
    },
    {
      "label": "Frusturated",
      "id": 3
    },
    {
      "label": "Overwhelmed",
      "id": 4
    }
  ]
}